warehouse14/__init__.py
warehouse14/forms.py
warehouse14/group_routes.py
warehouse14/login.py
warehouse14/models.py
warehouse14/pkg_helpers.py
warehouse14/repos.py
warehouse14/repos_dynamo.py
warehouse14/simple_api.py
warehouse14/static/css/materialize.css
warehouse14/static/css/materialize.min.css
warehouse14/static/css/pygments.css
warehouse14/static/css/style.css
warehouse14/static/js/materialize.js
warehouse14/static/js/materialize.min.js
warehouse14/storage.py
warehouse14/templates/account/account.html
warehouse14/templates/account/token.html
warehouse14/templates/base.html
warehouse14/templates/group/groups.html
warehouse14/templates/home.html
warehouse14/templates/project/create_project.html
warehouse14/templates/project/project.html
warehouse14/templates/project/project_edit.html
warehouse14/templates/project/project_users.html
warehouse14/templates/project/projects.html
warehouse14/templates/simple/links.html
warehouse14/templates/simple/simple.html
warehouse14-0.2.0.dist-info/LICENSE
warehouse14-0.2.0.dist-info/METADATA
warehouse14-0.2.0.dist-info/WHEEL
warehouse14-0.2.0.dist-info/RECORD
