Metadata-Version: 2.1
Name: warehouse14
Version: 0.2.0
Summary: A PyPI implementation for closed groups with authentication only
Home-page: https://github.com/eruvanos/warehouse14
License: MIT
Keywords: pypi
Author: Maic Siemering
Author-email: maic@siemering.tech
Requires-Python: >=3.8,<4.0
Classifier: Development Status :: 3 - Alpha
Classifier: License :: OSI Approved :: MIT License
Classifier: Programming Language :: Python :: 3
Classifier: Programming Language :: Python :: 3.8
Classifier: Programming Language :: Python :: 3.9
Classifier: Programming Language :: Python :: 3.10
Classifier: Programming Language :: Python :: 3.11
Classifier: Programming Language :: Python :: 3 :: Only
Classifier: Programming Language :: Python :: 3.10
Classifier: Programming Language :: Python :: 3.8
Classifier: Programming Language :: Python :: 3.9
Classifier: Topic :: Software Development
Classifier: Topic :: System :: Software Distribution
Provides-Extra: aws
Requires-Dist: authlib (>=1.2.0,<2.0.0)
Requires-Dist: flask (>=2.0.1,<3.0.0)
Requires-Dist: flask-httpauth (>=4.4.0,<5.0.0)
Requires-Dist: flask-login (>=0.6.2,<0.7.0)
Requires-Dist: flask-markdown (>=0.3,<0.4)
Requires-Dist: flask-wtf (>=1.1.1,<2.0.0)
Requires-Dist: pydantic (>=1.8.2,<2.0.0)
Requires-Dist: pypitoken (>=6.0.3,<7.0.0)
Requires-Dist: readme-renderer[md] (>=37.3,<38.0)
Requires-Dist: requests (>=2.25.1,<3.0.0)
Project-URL: Issue Tracker, https://github.com/eruvanos/warehouse14/issues
Project-URL: Repository, https://github.com/eruvanos/warehouse14
Project-URL: Roadmap, https://github.com/eruvanos/warehouse14/projects/1
